odoo/addons/purchase_representative/README.rst
odoo/addons/purchase_representative/__init__.py
odoo/addons/purchase_representative/__manifest__.py
odoo/addons/purchase_representative/i18n/it.po
odoo/addons/purchase_representative/i18n/purchase_representative.pot
odoo/addons/purchase_representative/models/__init__.py
odoo/addons/purchase_representative/models/stock_rule.py
odoo/addons/purchase_representative/readme/CONTRIBUTORS.md
odoo/addons/purchase_representative/readme/DESCRIPTION.md
odoo/addons/purchase_representative/readme/USAGE.md
odoo/addons/purchase_representative/static/description/icon.png
odoo/addons/purchase_representative/static/description/index.html
odoo/addons/purchase_representative/tests/__init__.py
odoo/addons/purchase_representative/tests/test_purchase_representative.py
odoo_addon_purchase_representative-18.0.1.0.0.4.dist-info/METADATA
odoo_addon_purchase_representative-18.0.1.0.0.4.dist-info/WHEEL
odoo_addon_purchase_representative-18.0.1.0.0.4.dist-info/top_level.txt
odoo_addon_purchase_representative-18.0.1.0.0.4.dist-info/RECORD
